abvelocity/get_data/cursor.py
abvelocity/get_data/data_container.py
abvelocity/get_data/get_asgmnt_data.py
abvelocity/get_data/get_expt_stats.py
abvelocity/get_data/get_metric_query.py
abvelocity/get_data/get_multi_expt_data.py
abvelocity/get_data/inspect_tables.py
abvelocity/get_data/join_expt_dfs.py
abvelocity/get_data/join_expt_with_metric_df.py
abvelocity/get_data/presto_cursor.py
abvelocity/get_data/query_info.py
abvelocity/get_data/sqlite_cursor.py
abvelocity/get_data/subsample_condition.py
abvelocity/journey/event/gen_event_query.py
abvelocity/journey/event/gen_event_tables_query.py
abvelocity/journey/seq/add_seq_elements_as_cols.py
abvelocity/journey/seq/conversion_query.py
abvelocity/journey/seq/count_seq_query.py
abvelocity/journey/seq/diff_query.py
abvelocity/journey/seq/gen_deduped_seq_query.py
abvelocity/journey/seq/gen_event_count_map_query.py
abvelocity/journey/seq/gen_fully_deduped_seq_query.py
abvelocity/journey/seq/gen_undeduped_seq_query.py
abvelocity/journey/seq/seq.py
abvelocity/journey/seq/seq_info.py
abvelocity/journey/seq/seq_query.py
abvelocity/journey/viz/create_sankey.py
abvelocity/journey/viz/create_sunburst.py
abvelocity/journey/viz/journey_barchart.py
abvelocity/journey/viz/sankey_plot.py
abvelocity/journey/viz/sunburst_plot.py
abvelocity/mea/get_mea_data.py
abvelocity/mea/mea.py
abvelocity/mea/run_mea.py
abvelocity/param/analysis_info.py
abvelocity/param/constants.py
abvelocity/param/derived_expt_stats.py
abvelocity/param/expt_info.py
abvelocity/param/get_hocon_conf.py
abvelocity/param/io_param.py
abvelocity/param/join_query.py
abvelocity/param/launch.py
abvelocity/param/launch_to_comparison_pair.py
abvelocity/param/launch_to_variant_list.py
abvelocity/param/metric.py
abvelocity/param/metric_family.py
abvelocity/param/metric_info.py
abvelocity/param/variant.py
abvelocity/sim/examples.py
abvelocity/sim/sim.py
abvelocity/stats/calc_variant_list_metric_stats.py
abvelocity/stats/calc_variant_metric_effects.py
abvelocity-0.1.0.dist-info/AUTHORS.rst
abvelocity-0.1.0.dist-info/LICENSE
abvelocity-0.1.0.dist-info/METADATA
abvelocity-0.1.0.dist-info/NOTICE
abvelocity-0.1.0.dist-info/WHEEL
abvelocity-0.1.0.dist-info/RECORD
