Metadata-Version: 2.3
Name: abvelocity
Version: 0.1.0
Summary: A Python package for accelerating data-driven experiments and analysis
License: BSD-2-Clause
Keywords: experiments,velocity,data-analysis,visualization,statistics
Author: Reza Hosseini
Author-email: reza1317@gmail.com
Requires-Python: >=3.10,<4.0
Classifier: Development Status :: 3 - Alpha
Classifier: Intended Audience :: Developers
Classifier: Intended Audience :: Science/Research
Classifier: License :: OSI Approved :: BSD License
Classifier: Programming Language :: Python :: 3
Classifier: Programming Language :: Python :: 3.10
Classifier: Programming Language :: Python :: 3.11
Classifier: Programming Language :: Python :: 3.12
Classifier: Programming Language :: Python :: 3.13
Requires-Dist: Jinja2 (>=3.1.0,<4.0.0)
Requires-Dist: numpy (>=2.0.0,<3.0.0)
Requires-Dist: pandas (>=2.2.0,<3.0.0)
Requires-Dist: plotly (>=5.24.0,<6.0.0)
Requires-Dist: presto-python-client (>=0.8.0,<0.9.0)
Requires-Dist: pyhocon (>=0.3.0,<0.4.0)
Requires-Dist: scipy (>=1.13.0,<2.0.0)
Requires-Dist: statsmodels (>=0.14.0,<0.15.0)
Requires-Dist: tabulate (>=0.9.0,<0.10.0)
